srt_fuzzy_sync/__init__.py
srt_fuzzy_sync/__main__.py
srt_fuzzy_sync/syncer.py
srt_fuzzy_sync-1.0.0.dist-info/METADATA
srt_fuzzy_sync-1.0.0.dist-info/WHEEL
srt_fuzzy_sync-1.0.0.dist-info/entry_points.txt
srt_fuzzy_sync-1.0.0.dist-info/RECORD
