Metadata-Version: 2.1
Name: srt-fuzzy-sync
Version: 1.0.0
Summary: 
License: MIT
Author: colin
Author-email: Colin_XKL@outlook.com
Requires-Python: >=3.8,<4.0
Classifier: License :: OSI Approved :: MIT License
Classifier: Programming Language :: Python :: 3
Classifier: Programming Language :: Python :: 3.8
Classifier: Programming Language :: Python :: 3.9
Classifier: Programming Language :: Python :: 3.10
Classifier: Programming Language :: Python :: 3.11
Requires-Dist: click (>=8.1.6,<9.0.0)
Requires-Dist: pysrt (>=1.1.2,<2.0.0)
Requires-Dist: rapidfuzz (>=3.1.1,<4.0.0)
